bfilter/__init__.py
bfilter/bloomfilter.py
bfilter/tests.py
bfilter-1.0.0.dist-info/DESCRIPTION.rst
bfilter-1.0.0.dist-info/METADATA
bfilter-1.0.0.dist-info/RECORD
bfilter-1.0.0.dist-info/WHEEL
bfilter-1.0.0.dist-info/metadata.json
bfilter-1.0.0.dist-info/top_level.txt
bfilter-1.0.0.dist-info/zip-safe
