Metadata-Version: 2.0
Name: bfilter
Version: 1.0.0
Summary: A Simple Bloom Filter for Python
Home-page: https://github.com/sysatom/python-bloom-filter
Author: sysatom
Author-email: sysatom@gmail.com
License: UNKNOWN
Keywords: data structures,bloom filter,bloom,filter,probabilistic
Platform: any
Classifier: Programming Language :: Python :: 3
Classifier: License :: OSI Approved :: MIT License
Classifier: Operating System :: OS Independent
Requires-Dist: bitarray (>=0.8.3)
Requires-Dist: mmh3 (>=2.5.1)
